coach_app_baml_client/__init__.py
coach_app_baml_client/baml_client/__init__.py
coach_app_baml_client/baml_client/async_client.py
coach_app_baml_client/baml_client/config.py
coach_app_baml_client/baml_client/globals.py
coach_app_baml_client/baml_client/inlinedbaml.py
coach_app_baml_client/baml_client/parser.py
coach_app_baml_client/baml_client/runtime.py
coach_app_baml_client/baml_client/stream_types.py
coach_app_baml_client/baml_client/sync_client.py
coach_app_baml_client/baml_client/tracing.py
coach_app_baml_client/baml_client/type_builder.py
coach_app_baml_client/baml_client/type_map.py
coach_app_baml_client/baml_client/types.py
coach_app_baml_client/baml_client/watchers.py
coach_app_baml_client-2.1.0.dist-info/METADATA
coach_app_baml_client-2.1.0.dist-info/WHEEL
coach_app_baml_client-2.1.0.dist-info/RECORD
